eepy/__init__.py
eepy/art.py
eepy/cat.py
eepy/point.py
eepy/test.py
eepy/zoo.py
eepy-0.3.55.dist-info/LICENSE
eepy-0.3.55.dist-info/METADATA
eepy-0.3.55.dist-info/WHEEL
eepy-0.3.55.dist-info/entry_points.txt
eepy-0.3.55.dist-info/top_level.txt
eepy-0.3.55.dist-info/RECORD
